purecrypt/__init__.py
purecrypt/__main__.py
purecrypt/b64.py
purecrypt/cli.py
purecrypt/crypt_abc.py
purecrypt/crypt_md5.py
purecrypt/crypt_sha2.py
purecrypt/crypt_sha256.py
purecrypt/crypt_sha512.py
purecrypt/limits.py
purecrypt/method.py
purecrypt/salt.py
py_purecrypt-0.1.1.dist-info/LICENSE
py_purecrypt-0.1.1.dist-info/METADATA
py_purecrypt-0.1.1.dist-info/WHEEL
py_purecrypt-0.1.1.dist-info/entry_points.txt
py_purecrypt-0.1.1.dist-info/top_level.txt
py_purecrypt-0.1.1.dist-info/RECORD
