Metadata-Version: 2.1
Name: py-purecrypt
Version: 0.1.1
Summary: A pure Python implementation of crypt(3) from GNU libc
Author: Carl Harris
License: Copyright 2023 Carl E. Harris Jr.
Requires-Python: >=3.10
License-File: LICENSE
Requires-Dist: cryptography
